entity_forge/__init__.py
entity_forge/_version.py
entity_forge/main.py
entity_forge/py.typed
entity_forge-0.1.0.dist-info/METADATA
entity_forge-0.1.0.dist-info/WHEEL
entity_forge-0.1.0.dist-info/entry_points.txt
entity_forge-0.1.0.dist-info/licenses/LICENSE
entity_forge-0.1.0.dist-info/RECORD
