Metadata-Version: 2.4
Name: entity-forge
Version: 0.1.0
Summary: Entity Forge - Entity intelligence service for NER and entity resolution
Project-URL: Homepage, https://github.com/darth-veitcher/entity-forge
Project-URL: Repository, https://github.com/darth-veitcher/entity-forge
Project-URL: Issues, https://github.com/darth-veitcher/entity-forge/issues
Author-email: darth-veitcher <1722315+darth-veitcher@users.noreply.github.com>
License: MIT
License-File: LICENSE
Keywords: entity-forge,entity-matching,entity-resolution,knowledge-graph,master-data-management,named-entity-recognition,ner
Classifier: Development Status :: 3 - Alpha
Classifier: Intended Audience :: Developers
Classifier: License :: OSI Approved :: MIT License
Classifier: Operating System :: OS Independent
Classifier: Programming Language :: Python :: 3
Classifier: Programming Language :: Python :: 3.11
Classifier: Programming Language :: Python :: 3.12
Classifier: Programming Language :: Python :: 3.13
Classifier: Topic :: Scientific/Engineering :: Artificial Intelligence
Classifier: Topic :: Software Development :: Libraries :: Python Modules
Classifier: Typing :: Typed
Requires-Python: >=3.11
Requires-Dist: fastapi>=0.115.0
Requires-Dist: pydantic-settings>=2.6.0
Requires-Dist: pydantic>=2.9.0
Requires-Dist: uvicorn[standard]>=0.32.0
